mseep_odoo_mcp-0.0.6.dist-info/licenses/LICENSE
odoo_mcp/__init__.py
odoo_mcp/__main__.py
odoo_mcp/odoo_client.py
odoo_mcp/server.py
mseep_odoo_mcp-0.0.6.dist-info/METADATA
mseep_odoo_mcp-0.0.6.dist-info/WHEEL
mseep_odoo_mcp-0.0.6.dist-info/entry_points.txt
mseep_odoo_mcp-0.0.6.dist-info/top_level.txt
mseep_odoo_mcp-0.0.6.dist-info/RECORD
